dingtalk_simple/__init__.py
dingtalk_simple/api/__init__.py
dingtalk_simple/api/base.py
dingtalk_simple/api/callback.py
dingtalk_simple/api/department.py
dingtalk_simple/api/user.py
dingtalk_simple/client/__init__.py
dingtalk_simple/client/base.py
dingtalk_simple/core/__init__.py
dingtalk_simple/core/constants.py
dingtalk_simple/core/exceptions.py
dingtalk_simple/core/utils.py
dingtalk_simple/crypto/__init__.py
dingtalk_simple/crypto/base.py
dingtalk_simple/crypto/cryptography.py
dingtalk_simple/crypto/pkcs7.py
dingtalk_simple/crypto/pycrypto.py
dingtalk_simple/storage/__init__.py
dingtalk_simple/storage/base.py
dingtalk_simple-0.0.2.dist-info/LICENSE
dingtalk_simple-0.0.2.dist-info/METADATA
dingtalk_simple-0.0.2.dist-info/WHEEL
dingtalk_simple-0.0.2.dist-info/top_level.txt
dingtalk_simple-0.0.2.dist-info/RECORD
